{
  "required": true,
  "minVersion": "0.8",
  "package": "net.borisshoes.arcananovum.mixins",
  "compatibilityLevel": "JAVA_21",
  "mixins": [
    "AbstractArrowAccessor",
    "AbstractArrowMixin",
    "AbstractContainerMenuMixin",
    "AvoidEntityGoalMixin",
    "BaseSpawnerMixin",
    "BellBlockEntityMixin",
    "BlockItemMixin",
    "CauldronInteractionDispatcherAccessor",
    "CauldronInteractionsMixin",
    "ChunkMapMixin",
    "ClearAllStatusEffectsConsumeEffectMixin",
    "ConditionsMixin",
    "CreeperMixin",
    "DamageSourceMixin",
    "DispenseItemBehaviorMixin",
    "EnchantmentHelperMixin",
    "EnchantmentMixin",
    "EntityAccessor",
    "EntityMixin",
    "ExperienceOrbMixin",
    "ExplosionMixin",
    "FarmBlockMixin",
    "FishingHookMixin",
    "HopperBlockEntityMixin",
    "InventoryMixin",
    "ItemCombinerMenuMixin",
    "ItemEntityMixin",
    "ItemStackMixin",
    "LivingEntityAccessor",
    "LivingEntityMixin",
    "LivingEntityVulnerabilityTrackMixin1",
    "LivingEntityVulnerabilityTrackMixin2",
    "LocalMobCapCalculatorMixin",
    "MinecraftServerMixin",
    "MobMixin",
    "MoveControlMixin",
    "NaturalSpawnerMixin",
    "PhantomMoveControlMixin",
    "PhantomSpawnerMixin",
    "PhantomSwoopGoalMixin",
    "PiglinAiMixin",
    "PlayerMixin",
    "PolymerBlockUtilsMixin",
    "PolymerItemUtilsMixin",
    "PoolElementStructurePieceMixin",
    "ProjectileWeaponItemMixin",
    "RegistryDataLoaderMixin",
    "RemoveStatusEffectsConsumeEffectMixin",
    "RepairItemRecipeMixin",
    "ServerEntityMixin",
    "ServerGamePacketListenerImplMixin",
    "ServerLevelMixin",
    "ServerPlayerEntityScreenHandlerListenerMixin",
    "ServerPlayerGameModeMixin",
    "ServerPlayerMixin",
    "SmithingTransformRecipeMixin",
    "SpawnerBlockEntityMixin",
    "StructureTemplatePoolAccessor",
    "TameAnimalTriggerMixin",
    "ThrowableItemProjectileAccessor",
    "ThrownTridentAccessor",
    "VoiceChatServerMixin",
    "WanderingTraderMixin",
    "WitherBossAccessor",
    "WitherBossMixin"
  ],
  "client": [
  ],
  "injectors": {
    "defaultRequire": 1
  }
}
